[ 
  {
    "name":"Awkward clap",
    "command":"$awkwardclap",
    "source":"https://youtu.be/ItN73Q4VRUU"
  },
  {
    "name":"Bébou ? 😳🥺",
    "command":"$bebou",
    "source":"https://youtu.be/dQw4w9WgXcQ"
  },
  {
    "name":"Bad to the Bone",
    "command":"$badtothebone",
    "source":"https://youtu.be/B0daj71rUSU"
  },
  {
    "name":"Bruh",
    "command":"$bruh",
    "source":"https://youtu.be/59qtpRxpNiI"
  },
  {
    "name":"Fart",
    "command":"$fart",
    "source":"https://youtu.be/tkc-Nwf5u9o"
  },
  {
    "name":"Knock",
    "command":"$knock",
    "source":"https://youtu.be/Xs-HbHCcK58"
  },
  {
    "name":"Laugh",
    "command":"$laugh",
    "source":"https://youtu.be/rEBjIfe7yjI"
  }
]
